frappeapi/__init__.py
frappeapi/applications.py
frappeapi/exception_handler.py
frappeapi/exceptions.py
frappeapi/fast_routes.py
frappeapi/responses.py
frappeapi/routing.py
frappeapi/utils.py
frappeapi/.mypy_cache/.gitignore
frappeapi/.mypy_cache/CACHEDIR.TAG
frappeapi/.mypy_cache/missing_stubs
frappeapi/.mypy_cache/3.12/@plugins_snapshot.json
frappeapi/.mypy_cache/3.12/__future__.data.json
frappeapi/.mypy_cache/3.12/__future__.meta.json
frappeapi/.mypy_cache/3.12/_ast.data.json
frappeapi/.mypy_cache/3.12/_ast.meta.json
frappeapi/.mypy_cache/3.12/_codecs.data.json
frappeapi/.mypy_cache/3.12/_codecs.meta.json
frappeapi/.mypy_cache/3.12/_collections_abc.data.json
frappeapi/.mypy_cache/3.12/_collections_abc.meta.json
frappeapi/.mypy_cache/3.12/_ctypes.data.json
frappeapi/.mypy_cache/3.12/_ctypes.meta.json
frappeapi/.mypy_cache/3.12/_decimal.data.json
frappeapi/.mypy_cache/3.12/_decimal.meta.json
frappeapi/.mypy_cache/3.12/_operator.data.json
frappeapi/.mypy_cache/3.12/_operator.meta.json
frappeapi/.mypy_cache/3.12/_random.data.json
frappeapi/.mypy_cache/3.12/_random.meta.json
frappeapi/.mypy_cache/3.12/_socket.data.json
frappeapi/.mypy_cache/3.12/_socket.meta.json
frappeapi/.mypy_cache/3.12/_thread.data.json
frappeapi/.mypy_cache/3.12/_thread.meta.json
frappeapi/.mypy_cache/3.12/_warnings.data.json
frappeapi/.mypy_cache/3.12/_warnings.meta.json
frappeapi/.mypy_cache/3.12/_weakref.data.json
frappeapi/.mypy_cache/3.12/_weakref.meta.json
frappeapi/.mypy_cache/3.12/_weakrefset.data.json
frappeapi/.mypy_cache/3.12/_weakrefset.meta.json
frappeapi/.mypy_cache/3.12/abc.data.json
frappeapi/.mypy_cache/3.12/abc.meta.json
frappeapi/.mypy_cache/3.12/array.data.json
frappeapi/.mypy_cache/3.12/array.meta.json
frappeapi/.mypy_cache/3.12/base64.data.json
frappeapi/.mypy_cache/3.12/base64.meta.json
frappeapi/.mypy_cache/3.12/binascii.data.json
frappeapi/.mypy_cache/3.12/binascii.meta.json
frappeapi/.mypy_cache/3.12/builtins.data.json
frappeapi/.mypy_cache/3.12/builtins.meta.json
frappeapi-0.3.0.dist-info/WHEEL
frappeapi-0.3.0.dist-info/METADATA
frappeapi-0.3.0.dist-info/RECORD
