Metadata-Version: 2.4
Name: frappeapi
Version: 0.3.0
Summary: FrappeAPI, FastAPI for Frappe Framework
Author-email: Muhammad Saif <muhamed.e.saif@gmail.com>
Requires-Python: >=3.10
Classifier: Development Status :: 4 - Beta
Classifier: Environment :: Web Environment
Classifier: Framework :: FastAPI
Classifier: Framework :: Pydantic
Classifier: Intended Audience :: Developers
Classifier: Intended Audience :: Information Technology
Classifier: Intended Audience :: System Administrators
Classifier: License :: OSI Approved :: MIT License
Classifier: Operating System :: OS Independent
Classifier: Programming Language :: Python :: 3 :: Only
Classifier: Programming Language :: Python :: 3.10
Classifier: Programming Language :: Python :: 3.11
Classifier: Programming Language :: Python :: 3.12
Classifier: Topic :: Internet
Classifier: Topic :: Internet :: WWW/HTTP
Classifier: Topic :: Internet :: WWW/HTTP :: HTTP Servers
Classifier: Topic :: Internet :: WWW/HTTP :: Dynamic Content
Classifier: Topic :: Internet :: WWW/HTTP :: WSGI :: Application
Classifier: Topic :: Software Development
Classifier: Topic :: Software Development :: Libraries
Classifier: Topic :: Software Development :: Libraries :: Application Frameworks
Classifier: Topic :: Software Development :: Libraries :: Python Modules
Classifier: Topic :: Software Development :: Code Generators
Classifier: Topic :: Software Development :: Object Brokering
Classifier: Topic :: Database
Classifier: Topic :: Database :: Database Engines/Servers
Classifier: Topic :: Database :: Front-Ends
Classifier: Typing :: Typed
Requires-Dist: pydantic==2.6.4,<3.0.0
Requires-Dist: typing-extensions>=4.12.2
Requires-Dist: Werkzeug>=2.3.8
Requires-Dist: fastapi~=0.115.2
Requires-Dist: python-multipart >=0.0.7
Requires-Dist: ruff>=0.2.2 ; extra == "dev"
Requires-Dist: pytest==8.2.2 ; extra == "dev"
Requires-Dist: pre-commit>=3.6.0 ; extra == "dev"
Requires-Dist: pytest==8.2.2 ; extra == "dev"
Project-URL: Documentation, https://github.com/0xsirsaif/frappe-api
Project-URL: Homepage, https://github.com/0xsirsaif/frappe-api
Project-URL: Repository, https://github.com/0xsirsaif/frappe-api
Provides-Extra: dev
